{
    "name": "Christine Seddon",
    "img": "https://avatars.githubusercontent.com/u/89155206?s=400&u=31553f1773ce6bdfa860b2bf3d6a710a46d5ee27&v=4",
    "email": "noddes@gmail.com",
    "links": {
      "website": "https://github.com/CSeddon01/cseddon_portfolio",
      "linkedin": "https://www.linkedin.com/in/christine-seddon-2a97a2158/",
      "github": "https://github.com/CSeddon01"
    },
    "jobTitle": "Full Stack Web Developer",
    "location": {
      "city": "Austin",
      "state": "TX",
      "country": "USA"
    }
  }