{
  "id": "1eb932ac-6ac2-4177-acee-bd774c45ea26",
  "name": "Meet Mehta",
  "img": "https://media.licdn.com/dms/image/C5103AQHvyda6VXgTnQ/profile-displayphoto-shrink_200_200/0?e=1576108800&v=beta&t=A7gmOBP-PtbBHlEmM9Cy-8pN4AjIxZ0uVChVJ1j6U-s",
  "links": {
    "website": "",
    "linkedin": "https://www.linkedin.com/in/meetmehta1103/",
    "github": "https://github.com/Meet1103"
  },
  "jobTitle": "Full Stack Web Developer",
  "location": {
    "city": "Rajkot",
    "state": "Gujarat",
    "country": "India"
  }
}
